flask_leaflet/__init__.py
flask_leaflet/basic_types.py
flask_leaflet/map.py
flask_leaflet/mixins.py
flask_leaflet/py.typed
flask_leaflet/layers/__init__.py
flask_leaflet/layers/base.py
flask_leaflet/layers/paths.py
flask_leaflet/layers/raster.py
flask_leaflet/layers/ui.py
flask_leaflet/static/images/marker-icon.png
flask_leaflet/static/images/marker-shadow.png
flask_leaflet/templates/load.html
flask_leaflet-0.2.4.dist-info/METADATA
flask_leaflet-0.2.4.dist-info/WHEEL
flask_leaflet-0.2.4.dist-info/top_level.txt
flask_leaflet-0.2.4.dist-info/RECORD
