Metadata-Version: 2.4
Name: flask-leaflet
Version: 0.2.4
Author-email: Sebastian Salinas <seba.salinas.delrio@gmail.com>
License-Expression: MIT
Project-URL: Homepage, https://github.com/sebasalinass/flask-tailwindcss
Requires-Python: >=3.11
Requires-Dist: flask<4,>=2
